fake_profile/__init__.py
fake_profile/generator.py
fake_profile-0.3.0.dist-info/LICENSE
fake_profile-0.3.0.dist-info/METADATA
fake_profile-0.3.0.dist-info/WHEEL
fake_profile-0.3.0.dist-info/top_level.txt
fake_profile-0.3.0.dist-info/RECORD
