Metadata-Version: 2.1
Name: fake-profile
Version: 0.3.0
Summary: This is a python package that helps developers to generate fake social media user profiles and interactions for development purposes
Home-page: https://github.com/C-o-m-o-n/fake_profile
Author: Collins O. Odhiambo
Author-email: comon928@gmail.com
Classifier: Programming Language :: Python :: 3
Classifier: Operating System :: OS Independent
Requires-Python: >=3.6
License-File: LICENSE
Requires-Dist: Faker
